[
  {
    "title": "Welcome to the Jungle",
    "imdb_id": "tt28540171",
    "type": "movie"
  },
  {
    "title": "Obsession",
    "imdb_id": "tt37287335",
    "type": "movie"
  },
  {
    "title": "Cocktail 2",
    "imdb_id": "tt35064672",
    "type": "movie"
  },
  {
    "title": "Toy Story 5",
    "imdb_id": "tt29355505",
    "type": "movie"
  },
  {
    "title": "Michael",
    "imdb_id": "tt11378946",
    "type": "movie"
  },
  {
    "title": "Supergirl",
    "imdb_id": "tt8814476",
    "type": "movie"
  },
  {
    "title": "The Sheep Detectives",
    "imdb_id": "tt32565993",
    "type": "movie"
  },
  {
    "title": "Mortal Kombat II",
    "imdb_id": "tt17490712",
    "type": "movie"
  },
  {
    "title": "Deep Water",
    "imdb_id": "tt29516222",
    "type": "movie"
  },
  {
    "title": "Disclosure Day",
    "imdb_id": "tt15047880",
    "type": "movie"
  },
  {
    "title": "Your Heart Will Be Broken",
    "imdb_id": "tt38190257",
    "type": "movie"
  },
  {
    "title": "Backrooms",
    "imdb_id": "tt26657236",
    "type": "movie"
  },
  {
    "title": "Bhooth Bangla",
    "imdb_id": "tt29540862",
    "type": "movie"
  },
  {
    "title": "Salitan",
    "imdb_id": "tt31240702",
    "type": "movie"
  },
  {
    "title": "Madness",
    "imdb_id": "tt0080075",
    "type": "movie"
  },
  {
    "title": "Damage",
    "imdb_id": "tt0104237",
    "type": "movie"
  },
  {
    "title": "The Super Mario Galaxy Movie",
    "imdb_id": "tt28650488",
    "type": "movie"
  },
  {
    "title": "Blast",
    "imdb_id": "tt37971394",
    "type": "movie"
  },
  {
    "title": "Voicemails for Isabelle",
    "imdb_id": "tt10375624",
    "type": "movie"
  },
  {
    "title": "The Mandalorian and Grogu",
    "imdb_id": "tt30825738",
    "type": "movie"
  }
]